pytexmk/__init__.py
pytexmk/__main__.py
pytexmk/additional.py
pytexmk/auxiliary_fun.py
pytexmk/check_version.py
pytexmk/compile.py
pytexmk/config.py
pytexmk/info_print.py
pytexmk/language.py
pytexmk/latexdiff.py
pytexmk/log_parser.py
pytexmk/logger_config.py
pytexmk/run.py
pytexmk/version.py
pytexmk/data/README.html
pytexmk/data/default_project_config.toml
pytexmk/data/default_user_config.toml
pytexmk/locale/en/LC_MESSAGES/__main__.mo
pytexmk/locale/en/LC_MESSAGES/additional.mo
pytexmk/locale/en/LC_MESSAGES/auxiliary_fun.mo
pytexmk/locale/en/LC_MESSAGES/check_version.mo
pytexmk/locale/en/LC_MESSAGES/compile.mo
pytexmk/locale/en/LC_MESSAGES/config.mo
pytexmk/locale/en/LC_MESSAGES/info_print.mo
pytexmk/locale/en/LC_MESSAGES/latexdiff.mo
pytexmk/locale/en/LC_MESSAGES/log_parser.mo
pytexmk/locale/en/LC_MESSAGES/logger_config.mo
pytexmk/locale/en/LC_MESSAGES/main.mo
pytexmk/locale/en/LC_MESSAGES/run.mo
pytexmk-1.0.4.251001.dist-info/licenses/LICENSE
pytexmk-1.0.4.251001.dist-info/METADATA
pytexmk-1.0.4.251001.dist-info/WHEEL
pytexmk-1.0.4.251001.dist-info/entry_points.txt
pytexmk-1.0.4.251001.dist-info/top_level.txt
pytexmk-1.0.4.251001.dist-info/RECORD
