Metadata-Version: 2.4
Name: pytexmk
Version: 1.0.4.251001
Summary: LaTeX 辅助编译命令行工具 LaTeX Auxiliary Compilation Command Line Tool
Author-email: 焱铭 <lxb-yanming@foxmail.com>
License-Expression: GPL-3.0-or-later
Project-URL: Homepage, https://github.com/YanMing-lxb/PyTeXMK
Project-URL: Bug Tracker, https://github.com/YanMing-lxb/PyTeXMK/issues
Keywords: LaTeX,build,latexmk
Classifier: Environment :: Console
Classifier: Intended Audience :: Developers
Classifier: Intended Audience :: End Users/Desktop
Classifier: Intended Audience :: Education
Classifier: Intended Audience :: Science/Research
Classifier: Programming Language :: Python :: 3.9
Classifier: Programming Language :: Python :: 3.10
Classifier: Programming Language :: Python :: 3.11
Classifier: Programming Language :: Python :: 3.12
Classifier: Operating System :: OS Independent
Requires-Python: >=3.9
License-File: LICENSE
Requires-Dist: packaging>=25.0
Requires-Dist: platformdirs>=4.3.8
Requires-Dist: pypdf>=5.8.0
Requires-Dist: rich>=14.0.0
Requires-Dist: rich-argparse>=1.7.1
Requires-Dist: toml>=0.10.2
Dynamic: license-file
